mountebank/__init__.py
mountebank/client.py
mountebank/exceptions.py
mountebank/stub/__init__.py
mountebank/stub/builder.py
mountebank/stub/predicates.py
mountebank/stub/response.py
mountebank-0.1.3.dist-info/DESCRIPTION.rst
mountebank-0.1.3.dist-info/METADATA
mountebank-0.1.3.dist-info/RECORD
mountebank-0.1.3.dist-info/WHEEL
mountebank-0.1.3.dist-info/metadata.json
mountebank-0.1.3.dist-info/top_level.txt
