Metadata-Version: 2.0
Name: mountebank
Version: 0.1.3
Summary: Mountebank for Python Developers
Home-page: https://github.com/kevinjqiu/py-mountebank
Author: Kevin Jing Qiu
Author-email: kevin@idempotent.ca
License: BSD
Keywords: mountebank,development,library,mock,test,stub
Platform: UNKNOWN
Classifier: Development Status :: 3 - Alpha
Classifier: Intended Audience :: Developers
Classifier: License :: OSI Approved :: BSD License
Classifier: Operating System :: Unix
Classifier: Operating System :: POSIX
Classifier: Operating System :: Microsoft :: Windows
Classifier: Programming Language :: Python
Classifier: Programming Language :: Python :: 2.7
Classifier: Programming Language :: Python :: 3
Classifier: Programming Language :: Python :: 3.3
Classifier: Programming Language :: Python :: 3.4
Classifier: Programming Language :: Python :: 3.5
Classifier: Programming Language :: Python :: Implementation :: CPython
Classifier: Programming Language :: Python :: Implementation :: PyPy
Classifier: Topic :: Utilities
Requires-Dist: requests (>=2.6)
Requires-Dist: six
